Flask_Gravatar-0.5.0.dist-info/DESCRIPTION.rst
Flask_Gravatar-0.5.0.dist-info/METADATA
Flask_Gravatar-0.5.0.dist-info/RECORD
Flask_Gravatar-0.5.0.dist-info/WHEEL
Flask_Gravatar-0.5.0.dist-info/metadata.json
Flask_Gravatar-0.5.0.dist-info/top_level.txt
flask_gravatar/__init__.py
flask_gravatar/version.py
