Metadata-Version: 1.1
Name: Flask-Gravatar
Version: 0.5.0
Summary: Small extension for Flask to make usage of Gravatar service easy.
Home-page: https://github.com/zzzsochi/Flask-Gravatar/
Author: Alexander Zelenyak aka ZZZ
Author-email: zzz.sochi@gmail.com
License: BSD
Keywords: flask gravatar
Platform: any
Classifier: Environment :: Web Environment
Classifier: Intended Audience :: Developers
Classifier: License :: OSI Approved :: BSD License
Classifier: Operating System :: OS Independent
Classifier: Programming Language :: Python
Classifier: Framework :: Flask
Classifier: Topic :: Internet :: WWW/HTTP :: Dynamic Content
Classifier: Topic :: Software Development :: Libraries :: Python Modules
Classifier: Programming Language :: Python :: 2
Classifier: Programming Language :: Python :: 2.7
Classifier: Programming Language :: Python :: 3
Classifier: Programming Language :: Python :: 3.4
Classifier: Programming Language :: Python :: 3.5
Classifier: Programming Language :: Python :: 3.6
Classifier: Development Status :: 5 - Production/Stable
